{
  "parent": "minecraft:recipes/root",
  "criteria": {
    "has_light_blue_dye": {
      "conditions": {
        "items": [
          {
            "tag": "c:dyes/light_blue"
          }
        ]
      },
      "trigger": "minecraft:inventory_changed"
    },
    "has_slimeball": {
      "conditions": {
        "items": [
          {
            "tag": "c:slime_balls"
          }
        ]
      },
      "trigger": "minecraft:inventory_changed"
    },
    "has_the_recipe": {
      "conditions": {
        "recipe": "tide:bobbers/light_blue"
      },
      "trigger": "minecraft:recipe_unlocked"
    }
  },
  "requirements": [
    [
      "has_slimeball",
      "has_light_blue_dye",
      "has_the_recipe"
    ]
  ],
  "rewards": {
    "recipes": [
      "tide:bobbers/light_blue"
    ]
  },
  "sends_telemetry_event": false
}